dls_toolkit/__init__.py
dls_toolkit/aws.py
dls_toolkit/gdrive/__init__.py
dls_toolkit/gdrive/auth.py
dls_toolkit/gdrive/gdrive.py
dls_toolkit/gdrive/services.py
dls_toolkit/gdrive/sheets.py
dls_toolkit-0.1.5.dist-info/WHEEL
dls_toolkit-0.1.5.dist-info/METADATA
dls_toolkit-0.1.5.dist-info/RECORD
